{
    "DNDConfig": null,
    "_height_": {
        "type": "string",
        "value": "80.24%"
    },
    "_left_": {
        "type": "string",
        "value": "2%"
    },
    "_margin_": [
        0,
        0,
        0,
        0
    ],
    "_orientation_": 6,
    "_padding_": [
        0,
        0,
        0,
        0
    ],
    "_percent_": true,
    "_skin_": "sa75c44a69034021a86f05742a075425",
    "_top_": {
        "type": "string",
        "value": "0%"
    },
    "_width_": {
        "type": "string",
        "value": "97px"
    },
    "allboxes": [],
    "autogrowmode": 0,
    "canUpdateUI": true,
    "centery": {
        "type": "string",
        "value": "50%"
    },
    "children": [
        "imgAddNewStep"
    ],
    "clipbounds": false,
    "containerweight": 100,
    "enablescrolling": true,
    "id": "flxBoxPlus",
    "info": null,
    "iscustomlayout": false,
    "isvisible": true,
    "kuid": "ea6dceaeab5f4c67aa135a70e77f7f91",
    "layouttype": 2,
    "name": "kony.ui.FlexContainer",
    "parent": "flxSteps",
    "pf": "frmStepComposition",
    "retaincontentalignment": false,
    "retainflexpositionproperties": false,
    "retainflowhorizontalalignment": false,
    "snapgridsize": 10,
    "snaptogrid": true,
    "wType": "FlexContainer",
    "widgetalignment": 1
}