{
    "@class": "com.kony.gen.viz.model.component.KVizImage2",
    "DNDConfig": null,
    "_base64_": null,
    "_height_": {
        "type": "string",
        "value": "50dp"
    },
    "_left_": {
        "type": "string",
        "value": "0dp"
    },
    "_margin_": [
        0,
        0,
        0,
        0
    ],
    "_padding_": [
        0,
        0,
        0,
        0
    ],
    "_skin_": "sbaca8b7c52b4bffbafc90964c5000f5",
    "_src_": "messenger.png",
    "_top_": {
        "type": "string",
        "value": "0dp"
    },
    "_width_": {
        "type": "string",
        "value": "30dp"
    },
    "canUpdateUI": true,
    "centerx": {
        "type": "string",
        "value": "20%"
    },
    "containerweight": 100,
    "id": "imgChat",
    "imagescalemode": 1,
    "info": null,
    "iscustomlayout": false,
    "isvisible": true,
    "kuid": "ce610084ab8844ddbb0450d4a5defa74",
    "name": "kony.ui.Image2",
    "parent": "flxRightIcons",
    "pf": "userwidgetmodel",
    "retaincontentalignment": false,
    "retainflexpositionproperties": false,
    "srcType": 1,
    "wType": "Image",
    "widgetalignment": 5
}