{
    "@class": "com.kony.gen.viz.model.container.KVizSegment2",
    "DNDConfig": null,
    "_bottom_": {
        "type": "string",
        "value": "-10dp"
    },
    "_data_": [
        {},
        {},
        {},
        {},
        {},
        {},
        {},
        {},
        {},
        {}
    ],
    "_height_": {
        "type": "string",
        "value": "101.85%"
    },
    "_indicator_": "none",
    "_margin_": [
        0,
        0,
        0,
        0
    ],
    "_orientation_": 2,
    "_padding_": [
        0,
        0,
        0,
        0
    ],
    "_right_": {
        "type": "string",
        "value": "-6dp"
    },
    "_width_": {
        "type": "string",
        "value": "99.07%"
    },
    "autogrowmode": 0,
    "canUpdateUI": true,
    "containerweight": 100,
    "counter": "09",
    "focusedindex": null,
    "focuseditem": null,
    "generatedtemplate": null,
    "groupcells": false,
    "hasSections": false,
    "id": "CopysegChannels0f48ce110672848",
    "ide_onRowClick": "AS_Segment_d6ff97e6b7fa4e36969ed4299ffb38be",
    "info": null,
    "ipad": {
        "psp": {
            "indicator": "rowselect"
        }
    },
    "iphone": {
        "psp": {
            "indicator": "rowselect"
        }
    },
    "iscustomlayout": false,
    "isvisible": true,
    "kuid": "gfb7a85fc769449887ad5c6cc3a5ca69",
    "masterdata": {},
    "name": "kony.ui.SegmentedUI2",
    "needpageindicator": true,
    "pageoffdotimage": "pageoffdot.png",
    "pageondotimage": "pageondot.png",
    "paginationconfig": {
        "position": "bottom"
    },
    "parent": "CopyflxChannelsCopy0hd617411bc1041",
    "pf": "frmDeleteUser",
    "retaincontentalignment": false,
    "retainflexpositionproperties": false,
    "retainselection": false,
    "rowTemplateId": "aba515c415004b8a8053cbb7d8641599",
    "rowcounter": 9,
    "rowfocusskin": "s6e7f07455ec411fbcf9e06217636f94",
    "rowskin": "sc4f7e6361364d3f810bc500daa8a11e",
    "rowtemplate": "flxChannels",
    "screenlevelwidget": false,
    "seccounter": 0,
    "sectionHeaderTemplateId": null,
    "sectionheaderskin": "s64f2a4ab45b4b1fb87d6b6429f052a8",
    "selectedRows": null,
    "selectedState": false,
    "selectedindex": null,
    "selectedindices": null,
    "selecteditems": null,
    "selectedsectionindex": null,
    "selectionbehavior": "default",
    "separatorcolor": "aaaaaa00",
    "separatorrequired": true,
    "separatorthickness": 1,
    "showscrollbars": false,
    "viewtype": "tableview",
    "vizProps": {},
    "wType": "Segment",
    "widgetalignment": 5,
    "widgetdatamap": {},
    "zindex": 1
}