{
    "@class": "com.kony.gen.viz.model.component.KVizButton",
    "DNDConfig": null,
    "_height_": {
        "type": "string",
        "value": "100%"
    },
    "_left_": {
        "type": "string",
        "value": "0dp"
    },
    "_margin_": [
        6,
        6,
        6,
        6
    ],
    "_padding_": [
        0,
        0,
        0,
        0
    ],
    "_skin_": "s312918df4cf49f79a1eb496bf33ef82",
    "_text_": "     Upload Labels",
    "_top_": {
        "type": "string",
        "value": "0dp"
    },
    "_width_": {
        "type": "string",
        "value": "100%"
    },
    "canUpdateUI": true,
    "containerweight": 100,
    "contentalignment": 5,
    "disabledSkins": {
        "focusSkin": "s6de8ee3e9e1463996d5dbb22b25b33b"
    },
    "displaytext": true,
    "id": "btnUploadLabels",
    "ide_onClick": "AS_Button_h188f600d5e34f588bbc057444214d22",
    "info": null,
    "iscustomlayout": false,
    "isvisible": true,
    "kuid": "g6be0ad2ecc247b4be5e42f057bcf6db",
    "name": "kony.ui.Button",
    "parent": "flxUploadLabels",
    "pf": "frmLabelManagement",
    "retaincontentalignment": false,
    "retainflexpositionproperties": false,
    "wType": "Button"
}