{
    "@class": "com.kony.gen.viz.model.container.KVizSegment2",
    "DNDConfig": null,
    "_data_": [
        [
            {
                "lb2": {
                    "@class": "com.viz.ide.model.segment.SimpleTextSegmentData",
                    "text": "it-IT",
                    "type": "Label"
                },
                "lb3": {
                    "@class": "com.viz.ide.model.segment.SimpleTextSegmentData",
                    "text": "de-DE",
                    "type": "Label"
                },
                "lb4": {
                    "@class": "com.viz.ide.model.segment.SimpleTextSegmentData",
                    "text": "fr-FR",
                    "type": "Label"
                },
                "lb5": {
                    "@class": "com.viz.ide.model.segment.SimpleTextSegmentData",
                    "text": "es-ES",
                    "type": "Label"
                },
                "lbl1": {
                    "@class": "com.viz.ide.model.segment.SimpleTextSegmentData",
                    "text": "en-US",
                    "type": "Label"
                }
            },
            [
                {
                    "lb1": {
                        "@class": "com.viz.ide.model.segment.SimpleTextSegmentData",
                        "text": "Prescription",
                        "type": "Label"
                    },
                    "lb2": {
                        "@class": "com.viz.ide.model.segment.SimpleTextSegmentData",
                        "text": "Prescrizione",
                        "type": "Label"
                    },
                    "lb3": {
                        "@class": "com.viz.ide.model.segment.SimpleTextSegmentData",
                        "text": "Verschreibung",
                        "type": "Label"
                    },
                    "lb4": {
                        "@class": "com.viz.ide.model.segment.SimpleTextSegmentData",
                        "text": "prescription",
                        "type": "Label"
                    },
                    "lb5": {
                        "@class": "com.viz.ide.model.segment.SimpleTextSegmentData",
                        "text": "prescripción",
                        "type": "Label"
                    }
                },
                {
                    "lb1": {
                        "@class": "com.viz.ide.model.segment.SimpleTextSegmentData",
                        "text": "More options",
                        "type": "Label"
                    },
                    "lb2": {
                        "@class": "com.viz.ide.model.segment.SimpleTextSegmentData",
                        "text": "Altre opzioni",
                        "type": "Label"
                    },
                    "lb3": {
                        "@class": "com.viz.ide.model.segment.SimpleTextSegmentData",
                        "text": "Weitere Optionen",
                        "type": "Label"
                    },
                    "lb4": {
                        "@class": "com.viz.ide.model.segment.SimpleTextSegmentData",
                        "text": "Plus d'options",
                        "type": "Label"
                    },
                    "lb5": {
                        "@class": "com.viz.ide.model.segment.SimpleTextSegmentData",
                        "text": "Más opciones",
                        "type": "Label"
                    }
                },
                {
                    "lb1": {
                        "@class": "com.viz.ide.model.segment.SimpleTextSegmentData",
                        "text": "Upload it now",
                        "type": "Label"
                    },
                    "lb2": {
                        "@class": "com.viz.ide.model.segment.SimpleTextSegmentData",
                        "text": "Caricala ora",
                        "type": "Label"
                    },
                    "lb3": {
                        "@class": "com.viz.ide.model.segment.SimpleTextSegmentData",
                        "text": "Jetzt hochladen",
                        "type": "Label"
                    },
                    "lb4": {
                        "@class": "com.viz.ide.model.segment.SimpleTextSegmentData",
                        "text": "Téléchargez-la maintenant",
                        "type": "Label"
                    },
                    "lb5": {
                        "@class": "com.viz.ide.model.segment.SimpleTextSegmentData",
                        "text": "Cárgala ahora",
                        "type": "Label"
                    }
                },
                {
                    "lb1": {
                        "@class": "com.viz.ide.model.segment.SimpleTextSegmentData",
                        "text": "Please try again",
                        "type": "Label"
                    },
                    "lb2": {
                        "@class": "com.viz.ide.model.segment.SimpleTextSegmentData",
                        "text": "Si prega di riprovare",
                        "type": "Label"
                    },
                    "lb3": {
                        "@class": "com.viz.ide.model.segment.SimpleTextSegmentData",
                        "text": "Bitte versuche es erneut",
                        "type": "Label"
                    },
                    "lb4": {
                        "@class": "com.viz.ide.model.segment.SimpleTextSegmentData",
                        "text": "Veuillez réessayer",
                        "type": "Label"
                    },
                    "lb5": {
                        "@class": "com.viz.ide.model.segment.SimpleTextSegmentData",
                        "text": "Inténtalo de nuevo",
                        "type": "Label"
                    }
                },
                {
                    "lb1": {
                        "@class": "com.viz.ide.model.segment.SimpleTextSegmentData",
                        "text": "Last updated:",
                        "type": "Label"
                    },
                    "lb2": {
                        "@class": "com.viz.ide.model.segment.SimpleTextSegmentData",
                        "text": "Caricata il:",
                        "type": "Label"
                    },
                    "lb3": {
                        "@class": "com.viz.ide.model.segment.SimpleTextSegmentData",
                        "text": "Hochgeladen am:",
                        "type": "Label"
                    },
                    "lb4": {
                        "@class": "com.viz.ide.model.segment.SimpleTextSegmentData",
                        "text": "Téléchargée en amont le:",
                        "type": "Label"
                    },
                    "lb5": {
                        "@class": "com.viz.ide.model.segment.SimpleTextSegmentData",
                        "text": "Subido en:",
                        "type": "Label"
                    }
                }
            ]
        ]
    ],
    "_height_": {
        "type": "string",
        "value": "100%"
    },
    "_indicator_": "none",
    "_left_": {
        "type": "string",
        "value": "0dp"
    },
    "_margin_": [
        0,
        0,
        0,
        0
    ],
    "_orientation_": 2,
    "_padding_": [
        0,
        0,
        0,
        0
    ],
    "_top_": {
        "type": "string",
        "value": "0dp"
    },
    "_width_": {
        "type": "string",
        "value": "100%"
    },
    "alternaterowskin": "sf3cedb126374af98263cddba1e668fc",
    "autogrowmode": 0,
    "canUpdateUI": true,
    "containerweight": 100,
    "counter": "04",
    "disabledSkins": {},
    "focusedindex": null,
    "focuseditem": null,
    "generatedtemplate": null,
    "groupcells": false,
    "hasSections": true,
    "id": "segLabels2",
    "info": null,
    "ipad": {
        "psp": {
            "indicator": "rowselect"
        }
    },
    "iphone": {
        "psp": {
            "indicator": "rowselect"
        }
    },
    "iscustomlayout": false,
    "isvisible": true,
    "kuid": "cdd5c9ef0326413296daa23f4fc9681e",
    "masterdata": {},
    "name": "kony.ui.SegmentedUI2",
    "needpageindicator": true,
    "pageoffdotimage": "pageoffdot.png",
    "pageondotimage": "pageondot.png",
    "paginationconfig": {
        "position": "bottom"
    },
    "parent": "flxScrollSegLabels2",
    "pf": "frmLabelManagement",
    "retaincontentalignment": false,
    "retainflexpositionproperties": false,
    "retainselection": false,
    "rowTemplateId": "f52fbfd9105d45b7a95d33b6887d33f0",
    "rowcounter": 4,
    "rowfocusskin": "s6e7f07455ec411fbcf9e06217636f94",
    "rowskin": "sc4f7e6361364d3f810bc500daa8a11e",
    "rowtemplate": "flxRowLabels",
    "screenlevelwidget": false,
    "seccounter": 0,
    "sectionHeaderTemplateId": "f89da6b2ac544be79fbf40e9e4c93231",
    "sectionheaderskin": "s64f2a4ab45b4b1fb87d6b6429f052a8",
    "sectionheadertemplate": "flxHeaderRowLabels",
    "selectedRows": null,
    "selectedState": false,
    "selectedindex": null,
    "selectedindices": null,
    "selecteditems": null,
    "selectedsectionindex": null,
    "selectionbehavior": "default",
    "separatorcolor": "ffffff00",
    "separatorrequired": true,
    "separatorthickness": 0,
    "showscrollbars": false,
    "viewtype": "tableview",
    "vizProps": {},
    "wType": "Segment",
    "widgetalignment": 5,
    "widgetdatamap": {
        "flxHeaderRowLabels": "flxHeaderRowLabels",
        "flxRowLabels": "flxRowLabels",
        "lb1": "lb1",
        "lb2": "lb2",
        "lb3": "lb3",
        "lb4": "lb4",
        "lb5": "lb5",
        "lbl1": "lbl1"
    },
    "zindex": 1
}